django_triflesoft_locations-0.3.1509281138.dist-info/DESCRIPTION.rst
django_triflesoft_locations-0.3.1509281138.dist-info/METADATA
django_triflesoft_locations-0.3.1509281138.dist-info/RECORD
django_triflesoft_locations-0.3.1509281138.dist-info/WHEEL
django_triflesoft_locations-0.3.1509281138.dist-info/metadata.json
django_triflesoft_locations-0.3.1509281138.dist-info/top_level.txt
locations/__init__.py
locations/admin.py
locations/models.py
